aiozipkin/__init__.py
aiozipkin/aiohttp_helpers.py
aiozipkin/constants.py
aiozipkin/context_managers.py
aiozipkin/helpers.py
aiozipkin/log.py
aiozipkin/mypy_types.py
aiozipkin/py.typed
aiozipkin/record.py
aiozipkin/sampler.py
aiozipkin/span.py
aiozipkin/tracer.py
aiozipkin/transport.py
aiozipkin/utils.py
aiozipkin-1.1.1.dist-info/LICENSE
aiozipkin-1.1.1.dist-info/METADATA
aiozipkin-1.1.1.dist-info/WHEEL
aiozipkin-1.1.1.dist-info/top_level.txt
aiozipkin-1.1.1.dist-info/zip-safe
aiozipkin-1.1.1.dist-info/RECORD
