Metadata-Version: 2.1
Name: aiozipkin
Version: 1.1.1
Summary: Distributed tracing instrumentation for asyncio application with zipkin
Home-page: https://github.com/aio-libs/aiozipkin
Author: Nikolay Novik
Author-email: nickolainovik@gmail.com
License: Apache 2
Download-URL: https://pypi.python.org/pypi/aiozipkin
Keywords: zipkin,distributed-tracing,tracing
Platform: POSIX
Classifier: License :: OSI Approved :: MIT License
Classifier: Intended Audience :: Developers
Classifier: Programming Language :: Python :: 3
Classifier: Programming Language :: Python :: 3.6
Classifier: Programming Language :: Python :: 3.7
Classifier: Programming Language :: Python :: 3.8
Classifier: Programming Language :: Python :: 3.9
Classifier: Operating System :: POSIX
Classifier: Development Status :: 5 - Production/Stable
Classifier: Framework :: AsyncIO
Requires-Python: >=3.6
License-File: LICENSE
